{"_type":"export","__export_format":4,"__export_date":"2023-04-11T00:53:43.122Z","__export_source":"insomnia.desktop.app:v2023.1.0","resources":[{"_id":"req_50c439fd385d454dad284943409455ea","parentId":"fld_c080bd3ba6d64029ba78229b8a9bc761","modified":1681174140344,"created":1675004897992,"url":"http://localhost:3333/login","name":"Login","description":"","method":"POST","body":{"mimeType":"application/json","text":"{\n\t\"email\": \"carla.braga29@gmail.com\",\n\t\"password\": \"12345\"\n}"},"parameters":[],"headers":[{"name":"Content-Type","value":"application/json"}],"authentication":{},"metaSortKey":-1675004897992,"isPrivate":false,"settingStoreCookies":true,"settingSendCookies":true,"settingDisableRenderRequestBody":false,"settingEncodeUrl":true,"settingRebuildPath":true,"settingFollowRedirects":"global","_type":"request"},{"_id":"fld_c080bd3ba6d64029ba78229b8a9bc761","parentId":"fld_629a370203e248b39b83dd70b33c2a1a","modified":1675004895284,"created":1675004895284,"name":"Autenticacao","description":"","environment":{},"environmentPropertyOrder":null,"metaSortKey":-1675004895284,"_type":"request_group"},{"_id":"fld_629a370203e248b39b83dd70b33c2a1a","parentId":"wrk_e5eb36f2042340328141339078e36aef","modified":1674792012494,"created":1674008615739,"name":"API","description":"","environment":{},"environmentPropertyOrder":null,"metaSortKey":-1674008615739,"_type":"request_group"},{"_id":"wrk_e5eb36f2042340328141339078e36aef","parentId":null,"modified":1674330207495,"created":1670372585129,"name":"tcc","description":"","scope":"design","_type":"workspace"},{"_id":"req_d9bb11d430b74d4c91fd681c0025e8d2","parentId":"fld_629a370203e248b39b83dd70b33c2a1a","modified":1678837230592,"created":1674339523577,"url":"https://hooks.slack.com/services/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","name":"notificar Slack","description":"","method":"GET","body":{"mimeType":"application/json","text":""},"parameters":[],"headers":[{"name":"Content-Type","value":"application/json"}],"authentication":{},"metaSortKey":-1674339523577,"isPrivate":false,"settingStoreCookies":true,"settingSendCookies":true,"settingDisableRenderRequestBody":false,"settingEncodeUrl":true,"settingRebuildPath":true,"settingFollowRedirects":"global","_type":"request"},{"_id":"req_20b34ebf617e457695a59b10d193adde","parentId":"fld_8b18e43e7da4406d902a688736dbd81b","modified":1678837205077,"created":1674515382747,"url":"http://localhost:3000/abi/Usuario","name":"Pegar ABI","description":"Esse endpoint retorna um json contendo as informações de ABI do contrato.\nEsse ABI é importante para que a conexão com um contrato seja estabelecida corretamente.","method":"GET","body":{},"parameters":[],"headers":[],"authentication":{},"metaSortKey":-1674515382747,"isPrivate":false,"settingStoreCookies":true,"settingSendCookies":true,"settingDisableRenderRequestBody":false,"settingEncodeUrl":true,"settingRebuildPath":true,"settingFollowRedirects":"global","_type":"request"},{"_id":"fld_8b18e43e7da4406d902a688736dbd81b","parentId":"fld_629a370203e248b39b83dd70b33c2a1a","modified":1674792045437,"created":1674440295414,"name":"Blockchain","description":"","environment":{},"environmentPropertyOrder":null,"metaSortKey":-1674337217779.5,"_type":"request_group"},{"_id":"req_6c2aadf7bc01498b9c37a936ff0d19a5","parentId":"fld_8b18e43e7da4406d902a688736dbd81b","modified":1678837153333,"created":1674440308196,"url":"{{ _.API_URL }}/blockchain/salvar/usuario","name":"Salvar Usuário","description":"Essa rota é responsável por salvar as informações de um usuário na BLOCKCHAIN.","method":"POST","body":{"mimeType":"application/json","text":"{\n\t\"email\": \"carla.braga29@gmail.com\",\n\t\"username\": \"CarlaBraga29\"\n}"},"parameters":[],"headers":[{"name":"Content-Type","value":"application/json"}],"authentication":{},"metaSortKey":-1674515382697,"isPrivate":false,"settingStoreCookies":true,"settingSendCookies":true,"settingDisableRenderRequestBody":false,"settingEncodeUrl":true,"settingRebuildPath":true,"settingFollowRedirects":"global","_type":"request"},{"_id":"req_dbc095f1ae0b45e99274e7d6102067a0","parentId":"fld_c454e85a1178430c9011b9aefec9467d","modified":1674439249850,"created":1674438358617,"url":"{{ _.API_URL }}/enderecos","name":"adicionar endereco","description":"","method":"PATCH","body":{"mimeType":"application/json","text":"{\n  \"pais\": \"Omã\",\n  \"estado\": \"Alagoas\",\n  \"cidade\": \"Fabrícia do Sul\",\n  \"logradouro\": \"Oliveira Rua\",\n  \"referencia\": \"62037\",\n  \"cep\": \"12022-588\",\n  \"coordenadas\": {\n    \"latitude\": \"84.5446\",\n    \"longitude\": \"-175.4432\"\n  },\n\t\"email\": \"Carla.Braga29@gmail.com\"\n}\n"},"parameters":[],"headers":[{"name":"Content-Type","value":"application/json"}],"authentication":{},"metaSortKey":-1674438358617,"isPrivate":false,"settingStoreCookies":true,"settingSendCookies":true,"settingDisableRenderRequestBody":false,"settingEncodeUrl":true,"settingRebuildPath":true,"settingFollowRedirects":"global","_type":"request"},{"_id":"fld_c454e85a1178430c9011b9aefec9467d","parentId":"fld_629a370203e248b39b83dd70b33c2a1a","modified":1674439608459,"created":1674438357553,"name":"Enderecos","description":"","environment":{},"environmentPropertyOrder":null,"metaSortKey":-1674334911982,"_type":"request_group"},{"_id":"req_7eb2fb1a78a74393a49adb8e4bf7116c","parentId":"fld_90ede511c22f4f50b7d1765f1d328b34","modified":1681077576150,"created":1674330303121,"url":"{{ _.API_URL }}/usuarios","name":"Criar usuário","description":"","method":"POST","body":{"mimeType":"application/json","text":"{\n\t\"nome\": \"Júlio\",\n\t\"sobrenome\": \"Pereira\",\n\t\"email\": \"Carla.Braga29@gmail.com\",\n\t\"username\": \"CarlaBraga29\",\n\t\"rg\": \"12345-6\",\n\t\"cpf\": \"123.456.789-10\",\n\t\"telefone\": \"(57) 6756-6692\",\n\t\"password\": \"12345\",\n\t\"repeat_password\": \"12345\",\n\t\"endereco\": {\"rua\": \"Goias\"}\n}"},"parameters":[],"headers":[{"name":"Content-Type","value":"application/json"}],"authentication":{},"metaSortKey":-1674330303121,"isPrivate":false,"settingStoreCookies":true,"settingSendCookies":true,"settingDisableRenderRequestBody":false,"settingEncodeUrl":true,"settingRebuildPath":true,"settingFollowRedirects":"global","_type":"request"},{"_id":"fld_90ede511c22f4f50b7d1765f1d328b34","parentId":"fld_629a370203e248b39b83dd70b33c2a1a","modified":1674330300387,"created":1674330300387,"name":"Usuário","description":"","environment":{},"environmentPropertyOrder":null,"metaSortKey":-1674330300387,"_type":"request_group"},{"_id":"req_da4b9f0102b2439d80868ce393e76def","parentId":"fld_90ede511c22f4f50b7d1765f1d328b34","modified":1674436747208,"created":1674436718200,"url":"{{ _.API_URL }}/usuarios/Carla.Braga29@gmail.com","name":"Excluir usuário","description":"","method":"DELETE","body":{},"parameters":[],"headers":[],"authentication":{},"metaSortKey":-1674169461061,"isPrivate":false,"settingStoreCookies":true,"settingSendCookies":true,"settingDisableRenderRequestBody":false,"settingEncodeUrl":true,"settingRebuildPath":true,"settingFollowRedirects":"global","_type":"request"},{"_id":"req_ed138cf160e74bbf93761c5dea60e00d","parentId":"fld_629a370203e248b39b83dd70b33c2a1a","modified":1674010859575,"created":1674008619001,"url":"http://localhost:3333/usuario","name":"New Request","description":"","method":"POST","body":{"mimeType":"application/json","text":"{\n  \"username\": \"matheus\",\n  \"email\": \"matheus@mate.com\",\n  \"password\": \"1234\",\n  \"repeat_password\": \"1234\",\n  \"nome\": \"matheus\",\n  \"sobrenome\": \"santos\",\n  \"rg\": \"360.118-7\",\n  \"cpf\": \"123.456.789-10\",\n  \"telefone\": \"3131231323\"\n}"},"parameters":[],"headers":[{"name":"Content-Type","value":"application/json"}],"authentication":{},"metaSortKey":-1674008619001,"isPrivate":false,"settingStoreCookies":true,"settingSendCookies":true,"settingDisableRenderRequestBody":false,"settingEncodeUrl":true,"settingRebuildPath":true,"settingFollowRedirects":"global","_type":"request"},{"_id":"env_33872955e22418c0294054213189cde5f7c05e65","parentId":"wrk_e5eb36f2042340328141339078e36aef","modified":1674330353808,"created":1670372585151,"name":"Base Environment","data":{"API_URL":"http://localhost:3333"},"dataPropertyOrder":{"&":["API_URL"]},"color":null,"isPrivate":false,"metaSortKey":1670372585151,"_type":"environment"},{"_id":"jar_33872955e22418c0294054213189cde5f7c05e65","parentId":"wrk_e5eb36f2042340328141339078e36aef","modified":1674340266628,"created":1670372585152,"name":"Default Jar","cookies":[{"key":"wa_lang_pref","value":"pt_br","expires":"2023-01-28T22:31:06.000Z","maxAge":604800,"domain":"whatsapp.com","path":"/","secure":true,"hostOnly":false,"creation":"2023-01-21T22:31:06.627Z","lastAccessed":"2023-01-21T22:31:06.627Z","id":"04398702487032913"},{"key":"wa_ul","value":"f4a9cd70-0ae0-43ed-aa66-e13c29edca47","expires":"2025-01-20T22:31:06.000Z","maxAge":63072000,"domain":"whatsapp.com","path":"/","secure":true,"httpOnly":true,"hostOnly":false,"creation":"2023-01-21T22:31:06.627Z","lastAccessed":"2023-01-21T22:31:06.627Z","id":"014501577079109484"}],"_type":"cookie_jar"},{"_id":"spc_ce48551d2bc64c54aa97b91709f4282f","parentId":"wrk_e5eb36f2042340328141339078e36aef","modified":1674330285214,"created":1670372585138,"fileName":"tcc","contents":"","contentType":"yaml","_type":"api_spec"},{"_id":"uts_f25bf6202b1f484f837cc101e7a83d87","parentId":"wrk_e5eb36f2042340328141339078e36aef","modified":1670372585154,"created":1670372585154,"name":"Example Test Suite","_type":"unit_test_suite"}]}